kiui/__init__.py
kiui/cam.py
kiui/config.py
kiui/env.py
kiui/equirect.py
kiui/geocalib.py
kiui/grid_put.py
kiui/lpips.py
kiui/mesh.py
kiui/mesh_utils.py
kiui/op.py
kiui/poser.py
kiui/quaternion.py
kiui/render.py
kiui/render_viser.py
kiui/slurm.py
kiui/sr.py
kiui/sys.py
kiui/timer.py
kiui/typing.py
kiui/utils.py
kiui/video.py
kiui/vis.py
kiui/agent/backend.py
kiui/agent/cli.py
kiui/agent/terminal.py
kiui/agent/utils.py
kiui/agent/tools/apply_patch.py
kiui/agent/tools/coder.py
kiui/assets/blender_lights/city.exr
kiui/assets/blender_lights/courtyard.exr
kiui/assets/blender_lights/forest.exr
kiui/assets/blender_lights/interior.exr
kiui/assets/blender_lights/license.txt
kiui/assets/blender_lights/night.exr
kiui/assets/blender_lights/studio.exr
kiui/assets/blender_lights/sunrise.exr
kiui/assets/blender_lights/sunset.exr
kiui/assets/lights/LICENSE.txt
kiui/assets/lights/bsdf_256_256.bin
kiui/assets/lights/mud_road_puresky_1k.hdr
kiui/cli/__init__.py
kiui/cli/aes.py
kiui/cli/bg.py
kiui/cli/blender_qremesh.py
kiui/cli/blender_render.py
kiui/cli/blip.py
kiui/cli/clip_sim.py
kiui/cli/clip_sim_text.py
kiui/cli/convert.py
kiui/cli/convert_fp16.py
kiui/cli/depth_midas.py
kiui/cli/depth_zoe.py
kiui/cli/dircmp.py
kiui/cli/hed.py
kiui/cli/lock_version.py
kiui/cli/pose.py
kiui/cli/remesh.py
kiui/cli/timer.py
kiui/cli/openpose/__init__.py
kiui/cli/openpose/body.py
kiui/cli/openpose/face.py
kiui/cli/openpose/hand.py
kiui/cli/openpose/model.py
kiui/cli/openpose/util.py
kiui/gridencoder/__init__.py
kiui/gridencoder/backend.py
kiui/gridencoder/grid.py
kiui/gridencoder/src/bindings.cpp
kiui/gridencoder/src/gridencoder.cu
kiui/gridencoder/src/gridencoder.h
kiui/nn/__init__.py
kiui/nn/attention_flash.py
kiui/nn/attention_xformers.py
kiui/nn/dit.py
kiui/nn/encoder.py
kiui/nn/flow_matching.py
kiui/nn/llm.py
kiui/nn/perciever.py
kiui/nn/sparse.py
kiui/nn/unet_2d.py
kiui/nn/unet_2d_cond.py
kiui/nn/unet_3d_cond.py
kiui/nn/utils.py
kiui/nn/vae_2d.py
kiui/nn/vae_3d.py
kiui-0.3.2.dist-info/licenses/LICENSE
kiui-0.3.2.dist-info/METADATA
kiui-0.3.2.dist-info/WHEEL
kiui-0.3.2.dist-info/entry_points.txt
kiui-0.3.2.dist-info/top_level.txt
kiui-0.3.2.dist-info/RECORD
