Metadata-Version: 2.4
Name: kiui
Version: 0.3.2
Summary: A toolkit for 3D vision
Author-email: kiui <ashawkey1999@gmail.com>
License:                                  Apache License
Project-URL: Homepage, https://github.com/ashawkey/kiuikit
Requires-Python: >=3.8
License-File: LICENSE
Requires-Dist: lazy_loader
Requires-Dist: varname
Requires-Dist: objprint
Requires-Dist: rich
Requires-Dist: pyyaml
Provides-Extra: full
Requires-Dist: torch; extra == "full"
Requires-Dist: tqdm; extra == "full"
Requires-Dist: numpy; extra == "full"
Requires-Dist: scipy; extra == "full"
Requires-Dist: scikit-image; extra == "full"
Requires-Dist: scikit-learn; extra == "full"
Requires-Dist: pandas; extra == "full"
Requires-Dist: trimesh; extra == "full"
Requires-Dist: pygltflib; extra == "full"
Requires-Dist: matplotlib; extra == "full"
Requires-Dist: opencv-python; extra == "full"
Requires-Dist: imageio; extra == "full"
Requires-Dist: imageio-ffmpeg; extra == "full"
Requires-Dist: dearpygui; extra == "full"
Requires-Dist: tyro; extra == "full"
Requires-Dist: viser; extra == "full"
Requires-Dist: pymeshlab; extra == "full"
Requires-Dist: huggingface_hub; extra == "full"
Requires-Dist: PyMCubes; extra == "full"
Requires-Dist: fbxloader; extra == "full"
Requires-Dist: envlight; extra == "full"
Requires-Dist: prompt_toolkit; extra == "full"
Requires-Dist: pygments; extra == "full"
Requires-Dist: openai; extra == "full"
Dynamic: license-file
